locallib/Bible.py
locallib/__init__.py
locallib/dat.py
locallib/exc.py
locallib/kjvdat.txt
locallib/pygui.py
locallib/pymath.py
locallib/pystrs.py
LocalLib-0.1.3.dist-info/LICENSE.txt
LocalLib-0.1.3.dist-info/METADATA
LocalLib-0.1.3.dist-info/WHEEL
LocalLib-0.1.3.dist-info/top_level.txt
LocalLib-0.1.3.dist-info/RECORD
