Metadata-Version: 2.1
Name: LocalLib
Version: 0.1.3
Summary: Makes easy tasks easier
Home-page: UNKNOWN
Author: sudopigeek
Author-email: samuelcatferrell@gmail.com
License: UNKNOWN
Platform: UNKNOWN
Classifier: Programming Language :: Python :: 3
Classifier: License :: OSI Approved :: MIT License
Classifier: Operating System :: OS Independent
Requires-Dist: win10toast (>=0.9)
